merge_koskidata2primusdata/__init__.py
merge_koskidata2primusdata/__main__.py
merge_koskidata2primusdata/add_column.py
merge_koskidata2primusdata/merge_student_years.py
merge_koskidata2primusdata-1.0.0.dist-info/LICENSE
merge_koskidata2primusdata-1.0.0.dist-info/METADATA
merge_koskidata2primusdata-1.0.0.dist-info/WHEEL
merge_koskidata2primusdata-1.0.0.dist-info/entry_points.txt
merge_koskidata2primusdata-1.0.0.dist-info/top_level.txt
merge_koskidata2primusdata-1.0.0.dist-info/RECORD
