Metadata-Version: 2.1
Name: merge-koskidata2primusdata
Version: 1.0.0
Summary: Utility which merging Koski and Primus CSV reports.
Home-page: https://github.com/pasiol/merge_koskidata2primusdata.git
Author: Pasi Ollikainen
Author-email: pasi.ollikainen@outlook.com
License: GNU Lesser General Public License v3.0 or later (LGPLv3.0+)
Platform: UNKNOWN
Classifier: Development Status :: 3 - Alpha
Classifier: License :: OSI Approved :: GNU Lesser General Public License v3 or later (LGPLv3+)
Classifier: Programming Language :: Python
Classifier: Programming Language :: Python :: 3.10
License-File: LICENSE
Requires-Dist: pandas (>=1.0.1)
Requires-Dist: numpy (>=1.18.1)
Requires-Dist: Click (>=7.0)
Requires-Dist: openpyxl (>=3.0.3)
Requires-Dist: xlrd (>=1.2.0)
